gnumake_tokenpool/__init__.py
gnumake_tokenpool/tokenpool.py
gnumake_tokenpool-0.0.9.dist-info/METADATA
gnumake_tokenpool-0.0.9.dist-info/WHEEL
gnumake_tokenpool-0.0.9.dist-info/top_level.txt
gnumake_tokenpool-0.0.9.dist-info/RECORD
