Metadata-Version: 2.4
Name: gnumake_tokenpool
Version: 0.0.9
Summary: jobclient and jobserver for the GNU make tokenpool protocol
Author-email: Milan Hauth <milahu@gmail.com>
License: MIT
Project-URL: Homepage, https://github.com/milahu/gnumake-tokenpool
Keywords: jobclient,jobserver,gnumake,tokenpool,jobqueue,job,queue,gnu,make
Classifier: Programming Language :: Python :: 3
Classifier: Topic :: Software Development :: Build Tools
Classifier: Topic :: Software Development :: Libraries
Classifier: License :: OSI Approved :: MIT License
